opalite/__init__.py
opalite/py.typed
opalite-0.1.0.dist-info/WHEEL
opalite-0.1.0.dist-info/METADATA
opalite-0.1.0.dist-info/RECORD
