Metadata-Version: 2.3
Name: opalite
Version: 0.1.0
Summary: A blazingly fast, modern and opinionated Python web framework that shines.
Author: Ramón Vila Ferreres
Author-email: Ramón Vila Ferreres <ramonvilafer@protonmail.com>
Requires-Python: >=3.13
